[
  {
    "BookName": "TSR11550 - Players Handbook",
    "BookShortName": "Players Handbook",
    "BookPublisher": "Wizards of the Coast",
    "BookCode": "TSR11550",
    "BookISBN": "0-7869-1550-1",
    "BookAuthor": "Monte Cook, Jonathan Tweet & Skip Williams",
    "BookPublished": "2000",
    "BookCover": "",
    "BookRules": "Dungeons and Dragons",
    "BookEdition": "3rd Edition",
    "BookPhysical": "No",
    "BookOwnedPDF": "No",
    "BookLibrary": "Yes",
    "BookSetting": "Core",
    "BookType": "Rulebook",
    "BookFormat": "Hardback",
    "BookSeries": "Rulebooks",
    "BookCharacterLevel": "",
    "BookPDF": [
      "D:\\Master Vault\\DnD\\3E\\TSR11550 - Players Handbook.pdf"
    ],
    "BookDescription": [
      "No description available."
    ],
    "TableOfContents": [
      {
    "title": "Book",
    "chapters": [
      {"page": 1, "title": "TOC TO BE DONE"},
      {"page": 2, "title": ""}
      ]    
  }
]
},
{
  "BookName": "TSR11551 - Dungeon Masters Guide",
  "BookShortName": "Dungeon Masters Guide",
  "BookPublisher": "Wizards of the Coast",
  "BookCode": "TSR11551",
  "BookISBN": "0-7869-1551-X",
  "BookAuthor": "Monte Cook, Jonathan Tweet & Skip Williams",
  "BookPublished": "",
  "BookCover": "",
  "BookRules": "Dungeons and Dragons",
  "BookEdition": "3rd Edition",
  "BookPhysical": "No",
  "BookOwnedPDF": "No",
  "BookLibrary": "Yes",
  "BookSetting": "Core",
  "BookType": "Rulebook",
  "BookFormat": "Hardback",
  "BookSeries": "Rulebooks",
  "BookCharacterLevel": "",
  "BookPDF": [
    "D:\\Master Vault\\DnD\\3E\\TSR11551 - Dungeon Masters Guide.pdf"
  ],
  "BookDescription": [
    "No description available."
  ],
  "TableOfContents": [
    {
  "title": "Book",
  "chapters": [
    {"page": 1, "title": "TOC TO BE DONE"},
    {"page": 2, "title": ""}
    ]    
}
]
},
{
  "BookName": "TSR11552 - Monster Manual",
  "BookShortName": "Monster Manual",
  "BookPublisher": "Wizards of the Coast",
  "BookCode": "TSR11552",
  "BookISBN": "0-7869-1552-8",
  "BookAuthor": "Monte Cook, Jonathan Tweet & Skip Williams",
  "BookPublished": "",
  "BookCover": "",
  "BookRules": "Dungeons and Dragons",
  "BookEdition": "3rd Edition",
  "BookPhysical": "No",
  "BookOwnedPDF": "No",
  "BookLibrary": "Yes",
  "BookSetting": "Core",
  "BookType": "Rulebook",
  "BookFormat": "Hardback",
  "BookSeries": "Rulebooks",
  "BookCharacterLevel": "",
  "BookPDF": [
    "D:\\Master Vault\\DnD\\3E\\TSR11552 - Monster Manual.pdf"
  ],
  "BookDescription": [
    "No description available."
  ],
  "TableOfContents": [
    {
  "title": "Book",
  "chapters": [
    {"page": 1, "title": "TOC TO BE DONE"},
    {"page": 2, "title": ""}
    ]    
}
]
},
{
  "BookName": "WTC882680000 - Monster Manual II",
  "BookShortName": "Monster Manual II",
  "BookPublisher": "Wizards of the Coast",
  "BookCode": "WTC882680000",
  "BookISBN": "",
  "BookAuthor": "",
  "BookPublished": "",
  "BookCover": "",
  "BookRules": "Dungeons and Dragons",
  "BookEdition": "3rd Edition",
  "BookPhysical": "No",
  "BookOwnedPDF": "No",
  "BookLibrary": "Yes",
  "BookSetting": "Core",
  "BookType": "Rulebook",
  "BookFormat": "Hardback",
  "BookSeries": "Core Rulebook Sequels",
  "BookCharacterLevel": "",
  "BookPDF": [
    "D:\\Master Vault\\DnD\\3E\\WTC882680000 - Monster Manual II.pdf"
  ],
  "BookDescription": [
    "No description available."
  ],
  "TableOfContents": [
    {
  "title": "Book",
  "chapters": [
    {"page": 1, "title": "TOC TO BE DONE"},
    {"page": 2, "title": ""}
    ]    
}
]
},
{
  "BookName": "WTC107977400 - The Sinister Spire",
  "BookShortName": "The Sinister Spire",
  "BookPublisher": "Wizards of the Coast",
  "BookCode": "WTC107977400",
  "BookISBN": "",
  "BookAuthor": "",
  "BookPublished": "",
  "BookCover": "",
  "BookRules": "Dungeons and Dragons",
  "BookEdition": "3rd Edition",
  "BookPhysical": "No",
  "BookOwnedPDF": "No",
  "BookLibrary": "Yes",
  "BookSetting": "Core",
  "BookType": "Adventure",
  "BookFormat": "",
  "BookSeries": "Adventures",
  "BookCharacterLevel": "",
  "BookPDF": [
    "D:\\Master Vault\\DnD\\3E\\WTC107977400 - The Sinister Spire.pdf"
  ],
  "BookDescription": [
    "No description available."
  ],
  "TableOfContents": [
    {
  "title": "Book",
  "chapters": [
    {"page": 1, "title": "TOC TO BE DONE"},
    {"page": 2, "title": ""}
    ]    
}
]
},
{
  "BookName": "WTC116400000 - The Sunless Citadel",
  "BookShortName": "The Sunless Citadel",
  "BookPublisher": "Wizards of the Coast",
  "BookCode": "WTC116400000",
  "BookISBN": "",
  "BookAuthor": "",
  "BookPublished": "",
  "BookCover": "",
  "BookRules": "Dungeons and Dragons",
  "BookEdition": "3rd Edition",
  "BookPhysical": "No",
  "BookOwnedPDF": "No",
  "BookLibrary": "Yes",
  "BookSetting": "Core",
  "BookType": "Adventure",
  "BookFormat": "",
  "BookSeries": "Adventures",
  "BookCharacterLevel": "",
  "BookPDF": [
    "D:\\Master Vault\\DnD\\3E\\WTC116400000 - The Sunless Citadel.pdf"
  ],
  "BookDescription": [
    "No description available."
  ],
  "TableOfContents": [
    {
  "title": "Book",
  "chapters": [
    {"page": 1, "title": "TOC TO BE DONE"},
    {"page": 2, "title": ""}
    ]    
}
]
},
{
  "BookName": "WTC786941960 - The Shattered Gates of Slaughtergarde",
  "BookShortName": "The Shattered Gates of Slaughtergarde",
  "BookPublisher": "Wizards of the Coast",
  "BookCode": "WTC786941960",
  "BookISBN": "",
  "BookAuthor": "",
  "BookPublished": "",
  "BookCover": "",
  "BookRules": "Dungeons and Dragons",
  "BookEdition": "3rd Edition",
  "BookPhysical": "No",
  "BookOwnedPDF": "No",
  "BookLibrary": "Yes",
  "BookSetting": "Core",
  "BookType": "Adventure",
  "BookFormat": "",
  "BookSeries": "Adventures",
  "BookCharacterLevel": "",
  "BookPDF": [
    "D:\\Master Vault\\DnD\\3E\\WTC786941960 - The Shattered Gates of Slaughtergarde.pdf"
  ],
  "BookDescription": [
    "No description available."
  ],
  "TableOfContents": [
    {
  "title": "Book",
  "chapters": [
    {"page": 1, "title": "TOC TO BE DONE"},
    {"page": 2, "title": ""}
    ]    
}
]
},
{
  "BookName": "WTC865750000 - The Forge of Fury",
  "BookShortName": "The Forge of Fury",
  "BookPublisher": "Wizards of the Coast",
  "BookCode": "WTC865750000",
  "BookISBN": "",
  "BookAuthor": "",
  "BookPublished": "",
  "BookCover": "",
  "BookRules": "Dungeons and Dragons",
  "BookEdition": "3rd Edition",
  "BookPhysical": "No",
  "BookOwnedPDF": "No",
  "BookLibrary": "Yes",
  "BookSetting": "Core",
  "BookType": "Adventure",
  "BookFormat": "",
  "BookSeries": "Adventures",
  "BookCharacterLevel": "",
  "BookPDF": [
    "D:\\Master Vault\\DnD\\3E\\WTC865750000 - The Forge of Fury.pdf"
  ],
  "BookDescription": [
    "No description available."
  ],
  "TableOfContents": [
    {
  "title": "Book",
  "chapters": [
    {"page": 1, "title": "TOC TO BE DONE"},
    {"page": 2, "title": ""}
    ]    
}
]
},
{
  "BookName": "WTC880620000 - The Speaker in Dreams",
  "BookShortName": "The Speaker in Dreams",
  "BookPublisher": "Wizards of the Coast",
  "BookCode": "WTC880620000",
  "BookISBN": "",
  "BookAuthor": "",
  "BookPublished": "",
  "BookCover": "",
  "BookRules": "Dungeons and Dragons",
  "BookEdition": "3rd Edition",
  "BookPhysical": "No",
  "BookOwnedPDF": "No",
  "BookLibrary": "Yes",
  "BookSetting": "Core",
  "BookType": "Adventure",
  "BookFormat": "",
  "BookSeries": "Adventures",
  "BookCharacterLevel": "",
  "BookPDF": [
    "D:\\Master Vault\\DnD\\3E\\WTC880620000 - The Speaker in Dreams.pdf"
  ],
  "BookDescription": [
    "No description available."
  ],
  "TableOfContents": [
    {
  "title": "Book",
  "chapters": [
    {"page": 1, "title": "TOC TO BE DONE"},
    {"page": 2, "title": ""}
    ]    
}
]
},
{
  "BookName": "WTC881630000 - Lord of the Iron Fortress",
  "BookShortName": "Lord of the Iron Fortress",
  "BookPublisher": "Wizards of the Coast",
  "BookCode": "WTC881630000",
  "BookISBN": "",
  "BookAuthor": "",
  "BookPublished": "",
  "BookCover": "",
  "BookRules": "Dungeons and Dragons",
  "BookEdition": "3rd Edition",
  "BookPhysical": "No",
  "BookOwnedPDF": "No",
  "BookLibrary": "Yes",
  "BookSetting": "Core",
  "BookType": "Adventure",
  "BookFormat": "",
  "BookSeries": "Adventures",
  "BookCharacterLevel": "",
  "BookPDF": [
    "D:\\Master Vault\\DnD\\3E\\WTC881630000 - Lord of the Iron Fortress.pdf"
  ],
  "BookDescription": [
    "No description available."
  ],
  "TableOfContents": [
    {
  "title": "Book",
  "chapters": [
    {"page": 1, "title": "TOC TO BE DONE"},
    {"page": 2, "title": ""}
    ]    
}
]
},
{
  "BookName": "WTC881670000 - Bastion of Broken Souls",
  "BookShortName": "Bastion of Broken Souls",
  "BookPublisher": "Wizards of the Coast",
  "BookCode": "WTC881670000",
  "BookISBN": "",
  "BookAuthor": "",
  "BookPublished": "",
  "BookCover": "",
  "BookRules": "Dungeons and Dragons",
  "BookEdition": "3rd Edition",
  "BookPhysical": "No",
  "BookOwnedPDF": "No",
  "BookLibrary": "Yes",
  "BookSetting": "Core",
  "BookType": "Adventure",
  "BookFormat": "",
  "BookSeries": "Adventures",
  "BookCharacterLevel": "",
  "BookPDF": [
    "D:\\Master Vault\\DnD\\3E\\WTC881670000 - Bastion of Broken Souls.pdf"
  ],
  "BookDescription": [
    "No description available."
  ],
  "TableOfContents": [
    {
  "title": "Book",
  "chapters": [
    {"page": 1, "title": "TOC TO BE DONE"},
    {"page": 2, "title": ""}
    ]    
}
]
},
{
  "BookName": "WTC882320000 - The Standing Stone",
  "BookShortName": "The Standing Stone",
  "BookPublisher": "Wizards of the Coast",
  "BookCode": "WTC882320000",
  "BookISBN": "",
  "BookAuthor": "",
  "BookPublished": "",
  "BookCover": "",
  "BookRules": "Dungeons and Dragons",
  "BookEdition": "3rd Edition",
  "BookPhysical": "No",
  "BookOwnedPDF": "No",
  "BookLibrary": "Yes",
  "BookSetting": "Core",
  "BookType": "Adventure",
  "BookFormat": "",
  "BookSeries": "Adventures",
  "BookCharacterLevel": "",
  "BookPDF": [
    "D:\\Master Vault\\DnD\\3E\\WTC882320000 - The Standing Stone.pdf"
  ],
  "BookDescription": [
    "No description available."
  ],
  "TableOfContents": [
    {
  "title": "Book",
  "chapters": [
    {"page": 1, "title": "TOC TO BE DONE"},
    {"page": 2, "title": ""}
    ]    
}
]
},
{
  "BookName": "WTC882370000 - Return to the Temple of Elemental Evil",
  "BookShortName": "Return to the Temple of Elemental Evil",
  "BookPublisher": "Wizards of the Coast",
  "BookCode": "WTC882370000",
  "BookISBN": "",
  "BookAuthor": "",
  "BookPublished": "",
  "BookCover": "",
  "BookRules": "Dungeons and Dragons",
  "BookEdition": "3rd Edition",
  "BookPhysical": "No",
  "BookOwnedPDF": "No",
  "BookLibrary": "Yes",
  "BookSetting": "Core",
  "BookType": "Adventure",
  "BookFormat": "",
  "BookSeries": "Adventures",
  "BookCharacterLevel": "",
  "BookPDF": [
    "D:\\Master Vault\\DnD\\3E\\WTC882370000 - Return to the Temple of Elemental Evil.pdf"
  ],
  "BookDescription": [
    "No description available."
  ],
  "TableOfContents": [
    {
  "title": "Book",
  "chapters": [
    {"page": 1, "title": "TOC TO BE DONE"},
    {"page": 2, "title": ""}
    ]    
}
]
},
{
  "BookName": "WTC882390000 - Heart of Nightfang Spire",
  "BookShortName": "Heart of Nightfang Spire",
  "BookPublisher": "Wizards of the Coast",
  "BookCode": "WTC882390000",
  "BookISBN": "",
  "BookAuthor": "",
  "BookPublished": "",
  "BookCover": "",
  "BookRules": "Dungeons and Dragons",
  "BookEdition": "3rd Edition",
  "BookPhysical": "No",
  "BookOwnedPDF": "No",
  "BookLibrary": "Yes",
  "BookSetting": "Core",
  "BookType": "Adventure",
  "BookFormat": "",
  "BookSeries": "Adventures",
  "BookCharacterLevel": "",
  "BookPDF": [
    "D:\\Master Vault\\DnD\\3E\\WTC882390000 - Heart of Nightfang Spire.pdf"
  ],
  "BookDescription": [
    "No description available."
  ],
  "TableOfContents": [
    {
  "title": "Book",
  "chapters": [
    {"page": 1, "title": "TOC TO BE DONE"},
    {"page": 2, "title": ""}
    ]    
}
]
},
{
  "BookName": "WTC886670000 - Deep Horizon",
  "BookShortName": "Deep Horizon",
  "BookPublisher": "Wizards of the Coast",
  "BookCode": "WTC886670000",
  "BookISBN": "",
  "BookAuthor": "",
  "BookPublished": "",
  "BookCover": "",
  "BookRules": "Dungeons and Dragons",
  "BookEdition": "3rd Edition",
  "BookPhysical": "No",
  "BookOwnedPDF": "No",
  "BookLibrary": "Yes",
  "BookSetting": "Core",
  "BookType": "Adventure",
  "BookFormat": "",
  "BookSeries": "Adventures",
  "BookCharacterLevel": "",
  "BookPDF": [
    "D:\\Master Vault\\DnD\\3E\\WTC886670000 - Deep Horizon.pdf"
  ],
  "BookDescription": [
    "No description available."
  ],
  "TableOfContents": [
    {
  "title": "Book",
  "chapters": [
    {"page": 1, "title": "TOC TO BE DONE"},
    {"page": 2, "title": ""}
    ]    
}
]
},
{
  "BookName": "WTC953827400 - Scourge of the Howling Horde",
  "BookShortName": "Scourge of the Howling Horde",
  "BookPublisher": "Wizards of the Coast",
  "BookCode": "WTC953827400",
  "BookISBN": "",
  "BookAuthor": "",
  "BookPublished": "",
  "BookCover": "",
  "BookRules": "Dungeons and Dragons",
  "BookEdition": "3rd Edition",
  "BookPhysical": "No",
  "BookOwnedPDF": "No",
  "BookLibrary": "Yes",
  "BookSetting": "Core",
  "BookType": "Adventure",
  "BookFormat": "",
  "BookSeries": "Adventures",
  "BookCharacterLevel": "",
  "BookPDF": [
    "D:\\Master Vault\\DnD\\3E\\WTC953827400 - Scourge of the Howling Horde.pdf"
  ],
  "BookDescription": [
    "No description available."
  ],
  "TableOfContents": [
    {
  "title": "Book",
  "chapters": [
    {"page": 1, "title": "TOC TO BE DONE"},
    {"page": 2, "title": ""}
    ]    
}
]
},
{
  "BookName": "WTC953857400 - Red Hand of Doom",
  "BookShortName": "Red Hand of Doom",
  "BookPublisher": "Wizards of the Coast",
  "BookCode": "WTC953857400",
  "BookISBN": "",
  "BookAuthor": "",
  "BookPublished": "",
  "BookCover": "",
  "BookRules": "Dungeons and Dragons",
  "BookEdition": "3rd Edition",
  "BookPhysical": "No",
  "BookOwnedPDF": "No",
  "BookLibrary": "Yes",
  "BookSetting": "Core",
  "BookType": "Adventure",
  "BookFormat": "",
  "BookSeries": "Adventures",
  "BookCharacterLevel": "",
  "BookPDF": [
    "D:\\Master Vault\\DnD\\3E\\WTC953857400 - Red Hand of Doom.pdf"
  ],
  "BookDescription": [
    "No description available."
  ],
  "TableOfContents": [
    {
  "title": "Book",
  "chapters": [
    {"page": 1, "title": "TOC TO BE DONE"},
    {"page": 2, "title": ""}
    ]    
}
]
},
{
  "BookName": "WTC959767400 - Barrow of the Forgotten King",
  "BookShortName": "Barrow of the Forgotten King",
  "BookPublisher": "Wizards of the Coast",
  "BookCode": "WTC959767400",
  "BookISBN": "",
  "BookAuthor": "",
  "BookPublished": "",
  "BookCover": "",
  "BookRules": "Dungeons and Dragons",
  "BookEdition": "3rd Edition",
  "BookPhysical": "No",
  "BookOwnedPDF": "No",
  "BookLibrary": "Yes",
  "BookSetting": "Core",
  "BookType": "Adventure",
  "BookFormat": "",
  "BookSeries": "Adventures",
  "BookCharacterLevel": "",
  "BookPDF": [
    "D:\\Master Vault\\DnD\\3E\\WTC959767400 - Barrow of the Forgotten King.pdf"
  ],
  "BookDescription": [
    "No description available."
  ],
  "TableOfContents": [
    {
  "title": "Book",
  "chapters": [
    {"page": 1, "title": "TOC TO BE DONE"},
    {"page": 2, "title": ""}
    ]    
}
]
},
{
  "BookName": "WTC109277400 - Fortress of the Yuan-ti",
  "BookShortName": "Fortress of the Yuan-ti",
  "BookPublisher": "Wizards of the Coast",
  "BookCode": "WTC109277400",
  "BookISBN": "",
  "BookAuthor": "",
  "BookPublished": "",
  "BookCover": "",
  "BookRules": "Dungeons and Dragons",
  "BookEdition": "3rd Edition",
  "BookPhysical": "No",
  "BookOwnedPDF": "No",
  "BookLibrary": "Yes",
  "BookSetting": "Core",
  "BookType": "Adventure",
  "BookFormat": "",
  "BookSeries": "Adventures",
  "BookCharacterLevel": "",
  "BookPDF": [
    "D:\\Master Vault\\DnD\\3E\\WTC109277400 - Fortress of the Yuan-ti.pdf"
  ],
  "BookDescription": [
    "No description available."
  ],
  "TableOfContents": [
    {
  "title": "Book",
  "chapters": [
    {"page": 1, "title": "TOC TO BE DONE"},
    {"page": 2, "title": ""}
    ]    
}
]
},
{
  "BookName": "WTC109257200 - Expedition to the Ruins of Greyhawk",
  "BookShortName": "Expedition to the Ruins of Greyhawk",
  "BookPublisher": "Wizards of the Coast",
  "BookCode": "WTC109257200",
  "BookISBN": "",
  "BookAuthor": "",
  "BookPublished": "",
  "BookCover": "",
  "BookRules": "Dungeons and Dragons",
  "BookEdition": "3rd Edition",
  "BookPhysical": "No",
  "BookOwnedPDF": "No",
  "BookLibrary": "Yes",
  "BookSetting": "Greyhawk",
  "BookType": "Expeditions",
  "BookFormat": "",
  "BookSeries": "Expedition Series",
  "BookCharacterLevel": "",
  "BookPDF": [
    "D:\\Master Vault\\DnD\\3E\\WTC109257200 - Expedition to the Ruins of Greyhawk.pdf"
  ],
  "BookDescription": [
    "No description available."
  ],
  "TableOfContents": [
    {
  "title": "Book",
  "chapters": [
    {"page": 1, "title": "TOC TO BE DONE"},
    {"page": 2, "title": ""}
    ]    
}
]
},
{
  "BookName": "WTC955687200 - Expedition to the Demonweb Pits",
  "BookShortName": "Expedition to the Demonweb Pits",
  "BookPublisher": "Wizards of the Coast",
  "BookCode": "WTC955687200",
  "BookISBN": "",
  "BookAuthor": "",
  "BookPublished": "",
  "BookCover": "",
  "BookRules": "Dungeons and Dragons",
  "BookEdition": "3rd Edition",
  "BookPhysical": "No",
  "BookOwnedPDF": "No",
  "BookLibrary": "Yes",
  "BookSetting": "Demonweb Pits",
  "BookType": "Expeditions",
  "BookFormat": "",
  "BookSeries": "Expedition Series",
  "BookCharacterLevel": "",
  "BookPDF": [
    "D:\\Master Vault\\DnD\\3E\\WTC955687200 - Expedition to the Demonweb Pits.pdf"
  ],
  "BookDescription": [
    "No description available."
  ],
  "TableOfContents": [
    {
  "title": "Book",
  "chapters": [
    {"page": 1, "title": "TOC TO BE DONE"},
    {"page": 2, "title": ""}
    ]    
}
]
},
{
  "BookName": "WTC953937200 - Expedition to Castle Ravenloft",
  "BookShortName": "Expedition to Castle Ravenloft",
  "BookPublisher": "Wizards of the Coast",
  "BookCode": "WTC953937200",
  "BookISBN": "",
  "BookAuthor": "",
  "BookPublished": "",
  "BookCover": "",
  "BookRules": "Dungeons and Dragons",
  "BookEdition": "3rd Edition",
  "BookPhysical": "No",
  "BookOwnedPDF": "No",
  "BookLibrary": "Yes",
  "BookSetting": "Ravenloft",
  "BookType": "Expeditions",
  "BookFormat": "",
  "BookSeries": "Expedition Series",
  "BookCharacterLevel": "",
  "BookPDF": [
    "D:\\Master Vault\\DnD\\3E\\WTC953937200 - Expedition to Castle Ravenloft.pdf"
  ],
  "BookDescription": [
    "No description available."
  ],
  "TableOfContents": [
    {
  "title": "Book",
  "chapters": [
    {"page": 1, "title": "TOC TO BE DONE"},
    {"page": 2, "title": ""}
    ]    
}
]
},
{
  "BookName": "TSR11742 - Gazetteer",
  "BookShortName": "Gazetteer",
  "BookPublisher": "Wizards of the Coast",
  "BookCode": "TSR11742",
  "BookISBN": "0-7869-1742-3",
  "BookAuthor": "Gary Holian, Erik Mona, Sean Reynolds & Frederick Weining",
  "BookPublished": "2000",
  "BookCover": "",
  "BookRules": "Dungeons and Dragons",
  "BookEdition": "3rd Edition",
  "BookPhysical": "Yes",
  "BookOwnedPDF": "No",
  "BookLibrary": "Yes",
  "BookSetting": "Oerth",
  "BookType": "Accessory",
  "BookFormat": "Softback",
  "BookSeries": "Accessories",
  "BookCharacterLevel": "",
  "BookPDF": [
    "D:\\Master Vault\\DnD\\3E\\TSR11742 - Gazetteer.pdf"
  ],
  "BookDescription": [
    "Welcome to the world of the D&D game!",
    "The Dungeons & Dragons world is a place where powerful creatures contest with ordinary men and women in a subtle war pitting good agasint evil, law against chaos.",
    "It is a world of magic, a world of mystery, a world of fantastic adventure -- all a backdrop for your own adventures.",
    "Inside is everything you need to launch your own version of the first campaign world, including:",
    "A full-color map of the land of the Flanaess, also showing the continentes and seas of the planet Oerth.",
    "A short history of the land.",
    "Descriptions of 60 countries, ready for adventure"
  ],
  "TableOfContents": [
    {
  "title": "Book",
  "chapters": [
    {"page": 1, "title": "TOC TO BE DONE"},
    {"page": 2, "title": ""}
    ]    
}
]
},
{
  "BookName": "TSR11743 - Living Greyhawk Gazetteer",
  "BookShortName": "Living Greyhawk Gazetteer",
  "BookPublisher": "Wizards of the Coast",
  "BookCode": "TSR11743",
  "BookISBN": "",
  "BookAuthor": "",
  "BookPublished": "",
  "BookCover": "",
  "BookRules": "Dungeons and Dragons",
  "BookEdition": "3rd Edition",
  "BookPhysical": "No",
  "BookOwnedPDF": "No",
  "BookLibrary": "Yes",
  "BookSetting": "Greyhawk",
  "BookType": "Accessory",
  "BookFormat": "",
  "BookSeries": "Accessories",
  "BookCharacterLevel": "",
  "BookPDF": [
    "D:\\Master Vault\\DnD\\3E\\TSR11743 - Living Greyhawk Gazetteer.pdf"
  ],
  "BookDescription": [
    "No description available."
  ],
  "TableOfContents": [
    {
  "title": "Book",
  "chapters": [
    {"page": 1, "title": "TOC TO BE DONE"},
    {"page": 2, "title": ""}
    ]    
}
]
},
{
  "BookName": "TSR11760 - Diablo II - Diablerie",
  "BookShortName": "Diablo II - Diablerie",
  "BookPublisher": "Wizards of the Coast",
  "BookCode": "TSR11760",
  "BookISBN": "",
  "BookAuthor": "JD Wiker",
  "BookPublished": "2000",
  "BookCover": "",
  "BookRules": "Dungeons and Dragons",
  "BookEdition": "3rd Edition",
  "BookPhysical": "No",
  "BookOwnedPDF": "No",
  "BookLibrary": "Yes",
  "BookSetting": "Diablo II",
  "BookType": "Accessory",
  "BookFormat": "",
  "BookSeries": "Diablo II",
  "BookCharacterLevel": "",
  "BookPDF": [
    "D:\\Master Vault\\DnD\\3E\\TSR11760  - Diablo II - Diablerie.pdf"
  ],
  "BookDescription": [
    "No description available."
  ],
  "TableOfContents": [
    {
  "title": "Book",
  "chapters": [
    {"page": 1, "title": "TOC TO BE DONE"},
    {"page": 2, "title": ""}
    ]    
}
]
},
{
  "BookName": "TSR11831 - To Hell and Back",
  "BookShortName": "To Hell and Back",
  "BookPublisher": "Wizards of the Coast",
  "BookCode": "TSR11831",
  "BookISBN": "",
  "BookAuthor": "Jason Carl, David Eckelberry, Jeff Quick & Rich Redman",
  "BookPublished": "2001",
  "BookCover": "",
  "BookRules": "Dungeons and Dragons",
  "BookEdition": "3rd Edition",
  "BookPhysical": "No",
  "BookOwnedPDF": "No",
  "BookLibrary": "Yes",
  "BookSetting": "Diablo II",
  "BookType": "Accessory",
  "BookFormat": "",
  "BookSeries": "Diablo II",
  "BookCharacterLevel": "",
  "BookPDF": [
    "D:\\Master Vault\\DnD\\3E\\TSR11831 - To Hell and Back.pdf"
  ],
  "BookDescription": [
    "No description available."
  ],
  "TableOfContents": [
    {
  "title": "Book",
  "chapters": [
    {"page": 1, "title": "TOC TO BE DONE"},
    {"page": 2, "title": ""}
    ]    
}
]
},
{
  "BookName": "WTC950037400 - Fane of the Drow",
  "BookShortName": "Fane of the Drow",
  "BookPublisher": "Wizards of the Coast",
  "BookCode": "WTC950037400",
  "BookISBN": "",
  "BookAuthor": "",
  "BookPublished": "",
  "BookCover": "",
  "BookRules": "Dungeons and Dragons",
  "BookEdition": "3rd Edition",
  "BookPhysical": "No",
  "BookOwnedPDF": "No",
  "BookLibrary": "Yes",
  "BookSetting": "",
  "BookType": "Fantastic Locations",
  "BookFormat": "",
  "BookSeries": "Fantastic Locations",
  "BookCharacterLevel": "",
  "BookPDF": [
    "D:\\Master Vault\\DnD\\3E\\WTC950037400 - Fane of the Drow.pdf"
  ],
  "BookDescription": [
    "No description available."
  ],
  "TableOfContents": [
    {
  "title": "Book",
  "chapters": [
    {"page": 1, "title": "TOC TO BE DONE"},
    {"page": 2, "title": ""}
    ]    
}
]
},
{
  "BookName": "WTC953640000 - Fields of Ruin",
  "BookShortName": "Fields of Ruin",
  "BookPublisher": "Wizards of the Coast",
  "BookCode": "WTC953640000",
  "BookISBN": "",
  "BookAuthor": "",
  "BookPublished": "",
  "BookCover": "",
  "BookRules": "Dungeons and Dragons",
  "BookEdition": "3rd Edition",
  "BookPhysical": "No",
  "BookOwnedPDF": "No",
  "BookLibrary": "Yes",
  "BookSetting": "",
  "BookType": "Fantastic Locations",
  "BookFormat": "",
  "BookSeries": "Fantastic Locations",
  "BookCharacterLevel": "",
  "BookPDF": [
    "D:\\Master Vault\\DnD\\3E\\WTC953640000 - Fields of Ruin.pdf"
  ],
  "BookDescription": [
    "No description available."
  ],
  "TableOfContents": [
    {
  "title": "Book",
  "chapters": [
    {"page": 1, "title": "TOC TO BE DONE"},
    {"page": 2, "title": ""}
    ]    
}
]
},
{
  "BookName": "WTC953777400 - Dragondown Grotto",
  "BookShortName": "Dragondown Grotto",
  "BookPublisher": "Wizards of the Coast",
  "BookCode": "WTC953777400",
  "BookISBN": "",
  "BookAuthor": "",
  "BookPublished": "",
  "BookCover": "",
  "BookRules": "Dungeons and Dragons",
  "BookEdition": "3rd Edition",
  "BookPhysical": "No",
  "BookOwnedPDF": "No",
  "BookLibrary": "Yes",
  "BookSetting": "",
  "BookType": "Fantastic Locations",
  "BookFormat": "",
  "BookSeries": "Fantastic Locations",
  "BookCharacterLevel": "",
  "BookPDF": [
    "D:\\Master Vault\\DnD\\3E\\WTC953777400 - Dragondown Grotto.pdf"
  ],
  "BookDescription": [
    "No description available."
  ],
  "TableOfContents": [
    {
  "title": "Book",
  "chapters": [
    {"page": 1, "title": "TOC TO BE DONE"},
    {"page": 2, "title": ""}
    ]    
}
]
},
{
  "BookName": "WTC957557400 - The Frostfell Rift",
  "BookShortName": "The Frostfell Rift",
  "BookPublisher": "Wizards of the Coast",
  "BookCode": "WTC957557400",
  "BookISBN": "",
  "BookAuthor": "",
  "BookPublished": "",
  "BookCover": "",
  "BookRules": "Dungeons and Dragons",
  "BookEdition": "3rd Edition",
  "BookPhysical": "No",
  "BookOwnedPDF": "No",
  "BookLibrary": "Yes",
  "BookSetting": "",
  "BookType": "Fantastic Locations",
  "BookFormat": "",
  "BookSeries": "Fantastic Locations",
  "BookCharacterLevel": "",
  "BookPDF": [
    "D:\\Master Vault\\DnD\\3E\\WTC957557400 - The Frostfell Rift.pdf"
  ],
  "BookDescription": [
    "No description available."
  ],
  "TableOfContents": [
    {
  "title": "Book",
  "chapters": [
    {"page": 1, "title": "TOC TO BE DONE"},
    {"page": 2, "title": ""}
    ]    
}
]
},
{
  "BookName": "WTC959787400 - City of Peril",
  "BookShortName": "City of Peril",
  "BookPublisher": "Wizards of the Coast",
  "BookCode": "WTC959787400",
  "BookISBN": "",
  "BookAuthor": "",
  "BookPublished": "",
  "BookCover": "",
  "BookRules": "Dungeons and Dragons",
  "BookEdition": "3rd Edition",
  "BookPhysical": "No",
  "BookOwnedPDF": "No",
  "BookLibrary": "Yes",
  "BookSetting": "",
  "BookType": "Fantastic Locations",
  "BookFormat": "",
  "BookSeries": "Fantastic Locations",
  "BookCharacterLevel": "",
  "BookPDF": [
    "D:\\Master Vault\\DnD\\3E\\WTC959787400 - City of Peril.pdf"
  ],
  "BookDescription": [
    "No description available."
  ],
  "TableOfContents": [
    {
  "title": "Book",
  "chapters": [
    {"page": 1, "title": "TOC TO BE DONE"},
    {"page": 2, "title": ""}
    ]    
}
]
},
{
  "BookName": "WTC950047400 - Hellspike Prison",
  "BookShortName": "Hellspike Prison",
  "BookPublisher": "Wizards of the Coast",
  "BookCode": "WTC950047400",
  "BookISBN": "",
  "BookAuthor": "",
  "BookPublished": "",
  "BookCover": "",
  "BookRules": "Dungeons and Dragons",
  "BookEdition": "3rd Edition",
  "BookPhysical": "No",
  "BookOwnedPDF": "No",
  "BookLibrary": "Yes",
  "BookSetting": "",
  "BookType": "Fantastic Locations",
  "BookFormat": "",
  "BookSeries": "Fantastic Locations",
  "BookCharacterLevel": "",
  "BookPDF": [
    "D:\\Master Vault\\DnD\\3E\\WTC950047400 - Hellspike Prison.pdf"
  ],
  "BookDescription": [
    "No description available."
  ],
  "TableOfContents": [
    {
  "title": "Book",
  "chapters": [
    {"page": 1, "title": "TOC TO BE DONE"},
    {"page": 2, "title": ""}
    ]    
}
]
}
]